recorpy/__init__.py
recorpy/reorder.py
recorpy/test/__init__.py
recorpy/test/test_reorder.py
recorpy-0.1.7.dist-info/LICENSE
recorpy-0.1.7.dist-info/WHEEL
recorpy-0.1.7.dist-info/METADATA
recorpy-0.1.7.dist-info/RECORD
