Metadata-Version: 2.1
Name: recorpy
Version: 0.1.7
Summary: ReCorPy is a small package to reorder correlation matrices from dataframes for better visualizations
Home-page: https://github.com/thebooort/ReCorPy
Keywords: correlation matrix,visualization,clustering
Author: thebooort
Author-email: 18428931+thebooort@users.noreply.github.com
Requires-Python: >=3.7,<4.0
Classifier: Programming Language :: Python :: 3
Classifier: Programming Language :: Python :: 3.10
Classifier: Programming Language :: Python :: 3.7
Classifier: Programming Language :: Python :: 3.8
Classifier: Programming Language :: Python :: 3.9
Requires-Dist: numpy (>=1.23.0,<2.0.0)
Requires-Dist: pandas (>=1.4.3,<2.0.0)
Requires-Dist: scikit-learn (>=1.1.1,<2.0.0)
Project-URL: Documentation, https://recorpy.readthedocs.io/en/latest/index.html
Project-URL: Repository, https://github.com/thebooort/ReCorPy
